{"_type":"export","__export_format":4,"__export_date":"2022-06-04T05:23:40.777Z","__export_source":"insomnia.desktop.app:v2022.3.0","resources":[{"_id":"req_1d87f9babd2c43f68c63b2e268a77632","parentId":"wrk_04237e0a314f4359903a3c5d69dc745f","modified":1654317103417,"created":1654316944636,"url":"{{ _.baseurl }}/icecream/5","name":"icecream","description":"","method":"GET","body":{},"parameters":[],"headers":[],"authentication":{},"metaSortKey":-1654316944636,"isPrivate":false,"settingStoreCookies":true,"settingSendCookies":true,"settingDisableRenderRequestBody":false,"settingEncodeUrl":true,"settingRebuildPath":true,"settingFollowRedirects":"global","_type":"request"},{"_id":"wrk_04237e0a314f4359903a3c5d69dc745f","parentId":null,"modified":1654316025725,"created":1654316025725,"name":"Ice Cream","description":"","scope":"collection","_type":"workspace"},{"_id":"req_6a89fed17cda407284f91ece29578adb","parentId":"wrk_04237e0a314f4359903a3c5d69dc745f","modified":1654317200017,"created":1654317099042,"url":"{{ _.baseurl }}/icecream","name":"icecream","description":"","method":"POST","body":{"mimeType":"application/json","text":"{\n  \"icecream\": \"🍨🍨🍨\"\n}"},"parameters":[],"headers":[{"name":"Content-Type","value":"application/json","id":"pair_0f7f1ddb545c45ee9bbd353174bcee6a"}],"authentication":{},"metaSortKey":-1654316944586,"isPrivate":false,"settingStoreCookies":true,"settingSendCookies":true,"settingDisableRenderRequestBody":false,"settingEncodeUrl":true,"settingRebuildPath":true,"settingFollowRedirects":"global","_type":"request"},{"_id":"env_169c39b4d9e7c19e79d221e49780f8ada945bfd1","parentId":"wrk_04237e0a314f4359903a3c5d69dc745f","modified":1654316891556,"created":1654316025735,"name":"Base Environment","data":{},"dataPropertyOrder":{},"color":null,"isPrivate":false,"metaSortKey":1654316025735,"_type":"environment"},{"_id":"jar_169c39b4d9e7c19e79d221e49780f8ada945bfd1","parentId":"wrk_04237e0a314f4359903a3c5d69dc745f","modified":1654316025737,"created":1654316025737,"name":"Default Jar","cookies":[],"_type":"cookie_jar"},{"_id":"spc_57d0097806124eff8416b9653373631c","parentId":"wrk_04237e0a314f4359903a3c5d69dc745f","modified":1654316025732,"created":1654316025732,"fileName":"Ice Cream","contents":"","contentType":"yaml","_type":"api_spec"},{"_id":"env_bbfa81623ac54352986242e6ebbb0d73","parentId":"env_169c39b4d9e7c19e79d221e49780f8ada945bfd1","modified":1654316925942,"created":1654316819577,"name":"localhost","data":{"baseurl":"http://localhost:8080/api"},"dataPropertyOrder":{"&":["baseurl"]},"color":null,"isPrivate":false,"metaSortKey":1654316819577,"_type":"environment"},{"_id":"env_405f04117b5d4b50a4c3a47da9625e1a","parentId":"env_169c39b4d9e7c19e79d221e49780f8ada945bfd1","modified":1654317189522,"created":1654316912250,"name":"aks","data":{"baseurl":"http://191.237.206.183:30000/api"},"dataPropertyOrder":{"&":["baseurl"]},"color":"#7d69cb","isPrivate":false,"metaSortKey":1654316912250,"_type":"environment"}]}